{
  "諸収入": {
    "本年度予算額": 2500000,
    "前年度予算額": null,
    "比較": null,
    "項": [
      {
        "諸収入": {
          "本年度予算額": 2500000,
          "目": [
            {
              "諸収入": {
                "本年度予算額": 2500000,
                "前年度予算額": null,
                "比較": null,
                "節": [
                  {
                    "諸収入": {
                      "金額": 2500000
                    }
                  }
                ]
              }
            }
          ]
        }
      }
    ]
  }
}